scripts/scripts/create_views.py
wspr_ai_lite/__init__.py
wspr_ai_lite/cli.py
wspr_ai_lite/fetch.py
wspr_ai_lite/ingest.py
wspr_ai_lite/tools.py
wspr_ai_lite/wspr_ai_lite.py
wspr_ai_lite/mcp/manifest.json
wspr_ai_lite/mcp/server.py
wspr_ai_lite-0.4.0.dist-info/licenses/LICENSE
wspr_ai_lite-0.4.0.dist-info/METADATA
wspr_ai_lite-0.4.0.dist-info/WHEEL
wspr_ai_lite-0.4.0.dist-info/entry_points.txt
wspr_ai_lite-0.4.0.dist-info/top_level.txt
wspr_ai_lite-0.4.0.dist-info/RECORD
