Metadata-Version: 2.4
Name: wspr-ai-lite
Version: 0.4.0
Summary: Lightweight WSPR analytics: DuckDB ingest + Streamlit dashboard.
Author: Greg Beam (KI7MT)
License-Expression: MIT
Project-URL: Homepage, https://github.com/KI7MT/wspr-ai-lite
Project-URL: Documentation, https://ki7mt.github.io/wspr-ai-lite/
Project-URL: Source, https://github.com/KI7MT/wspr-ai-lite
Project-URL: Issues, https://github.com/KI7MT/wspr-ai-lite/issues
Project-URL: Changelog, https://github.com/KI7MT/wspr-ai-lite/blob/main/CHANGELOG.md
Keywords: wspr,ham radio,duckdb,streamlit,amateur radio,analytics
Classifier: Development Status :: 4 - Beta
Classifier: Intended Audience :: Science/Research
Classifier: Intended Audience :: Developers
Classifier: Programming Language :: Python :: 3.11
Classifier: Programming Language :: Python :: 3.12
Classifier: Programming Language :: Python :: 3.13
Classifier: Operating System :: OS Independent
Classifier: Topic :: Scientific/Engineering :: Information Analysis
Classifier: Environment :: Console
Requires-Python: >=3.11
License-File: LICENSE
Requires-Dist: duckdb>=1.3.0
Requires-Dist: streamlit>=1.48.0
Requires-Dist: pandas>=2.2
Requires-Dist: requests>=2.31
Provides-Extra: dev
Requires-Dist: pytest; extra == "dev"
Requires-Dist: pre-commit; extra == "dev"
Requires-Dist: build; extra == "dev"
Requires-Dist: hatchling>=1.25; extra == "dev"
Provides-Extra: mcp
Provides-Extra: docs
Requires-Dist: mkdocs; extra == "docs"
Requires-Dist: mkdocs-material; extra == "docs"
Requires-Dist: mkdocs-macros-plugin; extra == "docs"
Dynamic: license-file
